{
    "version": "0.0.1",
    "generators": [
        {
            "generator": "Khronos Blender glTF 2.0 exporter",
            "name": "Blender exporter",
            "author": "Khronos Group",
            "docsURL": "https://github.com/KhronosGroup/glTF-Blender-Exporter",
            "bugsURL": "https://github.com/KhronosGroup/glTF-Blender-Exporter/issues"
        },
        {
            "generator": "blendergltf v*",
            "name": "Blender exporter",
            "author": "Kupoman",
            "docsURL": "https://github.com/Kupoman/blendergltf",
            "bugsURL": "https://github.com/Kupoman/blendergltf/issues"
        },
        {
            "generator": "COLLADA2GLTF",
            "name": "COLLADA2GLTF",
            "author": "Khronos Group",
            "docsURL": "https://github.com/KhronosGroup/COLLADA2GLTF",
            "bugsURL": "https://github.com/KhronosGroup/COLLADA2GLTF/issues"
        },
        {
            "generator": "Microsoft GLTF Exporter *",
            "name": "Microsoft exporter",
            "author": "Microsoft",
            "bugsText": "From the Feedback Hub on Windows, use the *Apps > Paint 3D* categorise."
        },
        {
            "generator": "Sketchup glTF Exporter by Centaur",
            "name": "Sketchup exporter",
            "author": "Centaur",
            "docsURL": "https://extensions.sketchup.com/content/gltf-exporter"
        },
        {
            "generator": "THREE.GLTFExporter",
            "name": "THREE.GLTFExporter",
            "author": "The three.js authors",
            "docsURL": "https://threejs.org/docs/#examples/exporters/GLTFExporter",
            "bugsURL": "https://github.com/mrdoob/three.js/issues"
        }
    ]
}
